odoo/addons/partner_country_lang/README.rst
odoo/addons/partner_country_lang/__init__.py
odoo/addons/partner_country_lang/__manifest__.py
odoo/addons/partner_country_lang/i18n/es.po
odoo/addons/partner_country_lang/i18n/partner_country_lang.pot
odoo/addons/partner_country_lang/models/__init__.py
odoo/addons/partner_country_lang/models/res_country.py
odoo/addons/partner_country_lang/models/res_partner.py
odoo/addons/partner_country_lang/readme/CONFIGURE.rst
odoo/addons/partner_country_lang/readme/CONTRIBUTORS.rst
odoo/addons/partner_country_lang/readme/DESCRIPTION.rst
odoo/addons/partner_country_lang/readme/USAGE.rst
odoo/addons/partner_country_lang/static/description/icon.png
odoo/addons/partner_country_lang/static/description/index.html
odoo/addons/partner_country_lang/tests/__init__.py
odoo/addons/partner_country_lang/tests/test_partner_country_lang.py
odoo/addons/partner_country_lang/views/res_country_view.xml
odoo13_addon_partner_country_lang-13.0.1.0.1.dev4.dist-info/METADATA
odoo13_addon_partner_country_lang-13.0.1.0.1.dev4.dist-info/WHEEL
odoo13_addon_partner_country_lang-13.0.1.0.1.dev4.dist-info/top_level.txt
odoo13_addon_partner_country_lang-13.0.1.0.1.dev4.dist-info/RECORD
